setup.py
textio/__init__.py
win_textio.egg-info/PKG-INFO
win_textio.egg-info/SOURCES.txt
win_textio.egg-info/dependency_links.txt
win_textio.egg-info/top_level.txt