Metadata-Version: 2.1
Name: win-textio
Version: 5.0.0
Summary: A Text Library
Home-page: UNKNOWN
Author: Monil Darediya
Author-email: monildarediya1@gmail.com
License: BSD
Keywords: TextEdits
Platform: UNKNOWN
Classifier: Development Status :: 2 - Pre-Alpha
Classifier: Topic :: Utilities
Classifier: License :: OSI Approved :: BSD License
Classifier: Operating System :: Microsoft :: Windows
